Phi/__init__.py
Phi/finished_methods.py
Phi/phi.dll
IRonTestTest-0.0.6.dist-info/LICENSE
IRonTestTest-0.0.6.dist-info/METADATA
IRonTestTest-0.0.6.dist-info/WHEEL
IRonTestTest-0.0.6.dist-info/top_level.txt
IRonTestTest-0.0.6.dist-info/RECORD
