Metadata-Version: 2.1
Name: IRonTestTest
Version: 0.0.6
Summary: A sample test package
Home-page: https://github.com/gituser/test-tackage
Author: berre
Author-email: berreergunn@gmail.com
License: MIT
Platform: UNKNOWN
Requires-Python: >=2
License-File: LICENSE
